cdktf_cdktf_provider_openstack/__init__.py
cdktf_cdktf_provider_openstack/py.typed
cdktf_cdktf_provider_openstack/_jsii/__init__.py
cdktf_cdktf_provider_openstack/_jsii/provider-openstack@1.0.0.jsii.tgz
cdktf_cdktf_provider_openstack/bgpvpn_network_associate_v2/__init__.py
cdktf_cdktf_provider_openstack/bgpvpn_port_associate_v2/__init__.py
cdktf_cdktf_provider_openstack/bgpvpn_router_associate_v2/__init__.py
cdktf_cdktf_provider_openstack/bgpvpn_v2/__init__.py
cdktf_cdktf_provider_openstack/blockstorage_qos_association_v3/__init__.py
cdktf_cdktf_provider_openstack/blockstorage_qos_v3/__init__.py
cdktf_cdktf_provider_openstack/blockstorage_quotaset_v3/__init__.py
cdktf_cdktf_provider_openstack/blockstorage_volume_attach_v3/__init__.py
cdktf_cdktf_provider_openstack/blockstorage_volume_type_access_v3/__init__.py
cdktf_cdktf_provider_openstack/blockstorage_volume_type_v3/__init__.py
cdktf_cdktf_provider_openstack/blockstorage_volume_v3/__init__.py
cdktf_cdktf_provider_openstack/compute_aggregate_v2/__init__.py
cdktf_cdktf_provider_openstack/compute_flavor_access_v2/__init__.py
cdktf_cdktf_provider_openstack/compute_flavor_v2/__init__.py
cdktf_cdktf_provider_openstack/compute_instance_v2/__init__.py
cdktf_cdktf_provider_openstack/compute_interface_attach_v2/__init__.py
cdktf_cdktf_provider_openstack/compute_keypair_v2/__init__.py
cdktf_cdktf_provider_openstack/compute_quotaset_v2/__init__.py
cdktf_cdktf_provider_openstack/compute_servergroup_v2/__init__.py
cdktf_cdktf_provider_openstack/compute_volume_attach_v2/__init__.py
cdktf_cdktf_provider_openstack/containerinfra_cluster_v1/__init__.py
cdktf_cdktf_provider_openstack/containerinfra_clustertemplate_v1/__init__.py
cdktf_cdktf_provider_openstack/containerinfra_nodegroup_v1/__init__.py
cdktf_cdktf_provider_openstack/data_openstack_blockstorage_availability_zones_v3/__init__.py
cdktf_cdktf_provider_openstack/data_openstack_blockstorage_quotaset_v3/__init__.py
cdktf_cdktf_provider_openstack-1.0.0.dist-info/LICENSE
cdktf_cdktf_provider_openstack-1.0.0.dist-info/METADATA
cdktf_cdktf_provider_openstack-1.0.0.dist-info/WHEEL
cdktf_cdktf_provider_openstack-1.0.0.dist-info/top_level.txt
cdktf_cdktf_provider_openstack-1.0.0.dist-info/RECORD
